<workunit>
    <invokers>
        <invoker folderid="/home/waterworks" caption="New Connection" index="0"  action="start"/>
    </invokers>
    
    <code class="com.rameses.gov.etracs.waterworks.models.WaterworksNewConnection" />
    
    <pageflow>
        <start>
            <transition to="create" />
        </start>
        <page name="init" title="New Account">
            <transition to="payment" caption="Next" />
        </page>
        <page name="payment" title="Payment Order">
            <transition to="init" caption="Back" />
            <transition to="end" caption="Next" />
        </page>
        <end/>
    </pageflow>
    
    <pages>
        <page name="create" template="com.rameses.gov.etracs.waterworks.views.NewAccountInitialPage"/>
        <page name="payment" template="com.rameses.gov.etracs.waterworks.views.NewAccountPaymentOrderPage"/>
    </pages>
</workunit>
