<schema adapter="market">

	<element tablename="market_application_task">
		<field name="taskid" primary="true"  prefix="MKTTSK"/>
		<complex name="app" ref="market_application" jointype="many-to-one" required="false"
			includefields="objid,appno,owner.name,acctname,dtfiled,unit.code,unit.unittype,unit.sector.name,unit.market.name"> 
			<key field="refid" target="objid"/>
		</complex>
		<field name="parentprocessid" />
		<field name="state" required="true"/>
		<field name="dtcreated" required="true"/>
		<field name="startdate" />
		<field name="enddate" />
		<field name="assignee_objid" />
		<field name="assignee_name" />
		<field name="actor_objid" />
		<field name="actor_name" />
		<field name="message" />	
		<field name="prevtaskid" />	
	</element>

</schema>