<workunit>
    <invokers>
        <invoker type="market:cashreceipt_payoption_type" caption="Specify No. of Months" 
                 index="0" visibleWhen="#{entity.payfrequency == 'MONTHLY'}"/>
    </invokers>
    
    <code>
        import com.rameses.rcp.annotations.*;
        
        class SpecifyNumberOfMonths {
        
            def context;
        
            def months = 0;
        
            def getValue() {
                return [
                    name:'NUM_MONTHS',
                    months: months
                ];
            }
        }
    </code>
    <pages>
        <page template="com.rameses.gov.etracs.market.views.SpecifyNumMonthsPayOptionPage" />
    </pages>
</workunit>
