<schema>
	<element name="mtoppermit" tablename="mtoppermit">
		<field name="objid" primary="true" />
		<field name="state" required="true" />
		<field name="txnno" required="true" />
		<field name="txndate" required="true" />
		<field name="owner_objid" required="true" />
		<field name="owner_name" required="true" />
		<field name="owner_address" required="true" />
		<field name="applicationid" required="true" />
		<field name="dtstarted" required="true" />
		<field name="dtexpired" required="true" />
	</element>
</schema>