<?xml version="1.0" encoding="UTF-8"?>
<workunit>
    <invokers>
        <invoker type="resection:open" action="open" caption="Resection" target="window"  />
         <!--  
        <invoker folderid="/explorer/txn/rpt/online" action="init"  caption="Resection" index="25"
            txntypeid="RS" txntype="Resection" newledger="false" newrpu="true" newrealproperpty="true" 
            role="APPRAISER" permission="resection.create" />

         <invoker type="quick_launcher" code="RS01" action="init"  caption="Resection" index="25"
            txntypeid="RS" txntype="Resection" newledger="false" newrpu="true" newrealproperpty="true" 
            role="APPRAISER" permission="resection.create" />
          --> 
          
   </invokers>
   
   <code class="com.rameses.gov.etracs.rpt.resection.ResectionController">
       
   </code>

    <pageflow>
        <start>
            <transition name="init" to="init"/>
            <transition name="open" to="open"/>
        </start>
        
        <page name="init" title="Resection: Initial Information">
            <transition caption="Cancel" to="end"  mnemonic="c" icon="images/toolbars/cancel.png"/>
            <transition caption="Next"  to="default" action="initResection" mnemonic="n"  />
        </page>
        
        <process name="open">
            <transition to="unassigned" cond="#{entity.taskstate &amp;&amp; entity.taskstate.matches('assign.*')}"/>
            <transition to="default" cond="#{entity.state == 'DRAFT'}"/>
            <transition to="taxmapping" cond="#{entity.state == 'FORTAXMAPPING'}"/>
            <transition to="forappraisal" cond="#{entity.state == 'FORAPPRAISAL'}"/>
            <transition to="forapproval" cond="#{entity.state == 'FORAPPROVAL'}"/>
            <transition to="forprovsubmission" cond="#{entity.state == 'FORPROVSUBMISSION'}"/>
            <transition to="forprovapproval" cond="#{entity.state == 'FORPROVAPPROVAL'}"/>
            <transition to="approved" cond="#{entity.state == 'APPROVED'}"/>
            <transition to="cancelled" cond="#{entity.state == 'CANCELLED'}"/>
        </process>
        
        <page name="unassigned" title="Resection (#{entity.state} - Unassigned)">
            <transition caption="Close"  to="end"      mnemonic="c" icon="images/toolbars/cancel.png" />
            <transition to="open" name="taxmapper" action="assignTaxmapper" caption="Assign To Me" role="TAXMAPPER"  visibleWhen="#{entity.taskstate == 'assign-taxmapper'}" confirm="Assign task to you?"/>
            <transition to="open" name="appraiser" action="assignAppraiser" caption="Assign To Me" role="APPRAISER" visibleWhen="#{entity.taskstate == 'assign-appraiser'}" confirm="Assign task to you?"/>
            <transition to="open" name="approver" action="assignApprover" caption="Assign To Me" role="APPROVER" visibleWhen="#{entity.taskstate == 'assign-approver'}" confirm="Assign task to you?"/>
        </page>
        
        <page name="default" title="Resection (Draft)">
            <transition caption="Close"  to="end"      mnemonic="c" icon="images/toolbars/cancel.png" />
            <transition caption="Delete" to="delete"  action="delete" confirm="Delete record?"    mnemonic="d" icon="images/toolbars/trash.png"  role="APPRAISER" permission="resection.delete" />
            <transition caption="Submit to Taxmapping" to="open" action="submitForTaxmapping"  mnemonic="m"   role="APPRAISER" permission="resection.submit" />
        </page>
        
        <process name="back-to-default">
            <transition to="default" />
        </process>
        
        <process name="delete">
            <transition to="end"/>
        </process>
        
        
        
        <page name="taxmapping" title="Resection (For Taxmapping)">
            <transition caption="Close"  to="end"      mnemonic="c" icon="images/toolbars/cancel.png" />
            <transition caption="Submit for Appraisal" to="open" action="submitForAppraisal"  mnemonic="m"    role="TAXMAPPER"/>
        </page>
        
        
        <page name="forappraisal" title="Resection (For Appraisal)">
            <transition caption="Close"  to="end"      mnemonic="c" icon="images/toolbars/cancel.png" />
            <transition caption="Submit for Approval" to="open" action="submitForApproval"  mnemonic="m"    role="APPRAISER"/>
        </page>
        
        <process name="submit">
            <transition to="forapproval" cond="#{entity.state == 'FORAPPROVAL'}"/>
            <transition to="forprovapproval" cond="#{entity.state == 'FORPROVAPPROVAL'}"/>
            <transition to="forprovsubmission" cond="#{entity.state == 'FORPROVSUBMISSION'}"/>
        </process>
        
        
        <!-- CITY-->
        <page name="forapproval" title="Resection (For Approval)">
            <transition caption="Close" to="end" mnemonic="c" icon="images/toolbars/cancel.png"  />
            <transition caption="Disapprove" to="default" action="disapproveResection" mnemonic="d"   role="APPROVER"/>
            <transition caption="Approve" to="wait" action="approveResection" mnemonic="v" icon="images/toolbars/approve.png"  confirm="Approve Resection?" role="APPROVER"/>
        </page>
        
        
        <page name="wait" title="Resection Approval">
            <transition caption="Back" to="forapproval" action="checkErrors" mnemonic="f" icon="images/toolbars/arrow_left.png" />
            <transition caption="Finish" to="approved" action="checkFinish" mnemonic="f" icon="images/toolbars/approve.png" />
        </page>        
        
        <process name="back-to-forapproval">
            <transition to="forapproval"/>
        </process>
        
        
        <!-- MUNICIPALIY -->
        <page name="forprovsubmission" title="Resection (For Submission to Province)">
            <transition caption="Close"  to="end" mnemonic="c" icon="images/toolbars/cancel.png"  />
            <transition caption="Edit"   to="back-to-prov-submission" action="edit" name="edit" mnemonic="e" shortcut="ctrl E" icon="images/toolbars/edit.png"   role="RECOMMENDER"/>
            <transition caption="Cancel" to="back-to-prov-submission" action="cancelEdit" name="cancel"  mnemonic="c" icon="images/toolbars/cancel.png" />
            <transition caption="Save"   to="back-to-prov-submission" action="save" name="save" mnemonic="s" shortcut="ctrl S" icon="images/toolbars/save.png"   />
            <transition caption="Disapprove" to="open" action="disapproveSubmitToProvice"  mnemonic="d"   role="RECOMMENDER"/>
            <transition caption="Submit to Province" to="open" action="submitToProvince" mnemonic="m"   role="RECOMMENDER"/>
        </page>
        
        <process name="back-to-prov-submission">
            <transition to="forprovsubmission"/>
        </process>
        
        <page name="provsubmissionapproval" title="Resection (For Province Approval)">
            <transition caption="Close" to="end" mnemonic="c" icon="images/toolbars/cancel.png"/>
            <transition caption="Disapprove" to="open" action="disapproveSubmittedToProvince"  mnemonic="d"  role="RECOMMENDER"/>
            <transition caption="Approve" to="approved" action="approveSubmittedToProvince"  mnemonic="v"  role="RECOMMENDER"/>
        </page>
        
        
        <!-- PROVINCE -->
        <page name="forprovapproval" title="Resection (Province Approval)">
            <transition caption="Close" to="end" mnemonic="c" icon="images/toolbars/cancel.png"  />
            <transition caption="Edit"   to="back-to-forprovapproval" action="edit" name="edit" mnemonic="e" shortcut="ctrl E" icon="images/toolbars/edit.png"    role="APPROVER"/>
            <transition caption="Cancel" to="back-to-forprovapproval" action="cancelEdit" name="cancel"  mnemonic="c" icon="images/toolbars/cancel.png" />
            <transition caption="Save"   to="back-to-forprovapproval" action="save" name="save" mnemonic="s" shortcut="ctrl S" icon="images/toolbars/save.png"   />
            <transition caption="Disapprove" to="open" action="disapproveByProvince"  mnemonic="d"    role="APPROVER"/>
            <transition caption="Approve" to="open" action="approveByProvince"  mnemonic="v"  confirm="Approve Resection?" role="APPROVER"/>
        </page>
        
        <process name="back-to-forprovapproval">
            <transition to="forprovapproval"/>
        </process>
        
        <page name="approved" title="Resection (Approved)">
            <transition caption="Close" to="end" mnemonic="c" icon="images/toolbars/cancel.png"/>
        </page>
        
        <end />
        
    </pageflow>
    
    <pages> 
        <page name="init" template="com.rameses.gov.etracs.rpt.resection.ResectionInitPage"/>
        <page name="unassigned" template="com.rameses.gov.etracs.rpt.workflow.InfoPage"/>
        <page name="wait" template="com.rameses.gov.etracs.rpt.rpu.ui.WaitInfoPage"/>
    </pages>
</workunit>


